Metadata-Version: 2.1
Name: odoo14-addon-edi_oca
Version: 14.0.1.27.0
Summary: Define backends, exchange types, exchange records, basic automation and views for handling EDI exchanges.
Home-page: https://github.com/OCA/edi
Author: ACSONE,Creu Blanca,Camptocamp,Odoo Community Association (OCA)
Author-email: support@odoo-community.org
License: LGPL-3
Classifier: Programming Language :: Python
Classifier: Framework :: Odoo
Classifier: Framework :: Odoo :: 14.0
Classifier: License :: OSI Approved :: GNU Lesser General Public License v3 (LGPLv3)
Classifier: Development Status :: 4 - Beta
Requires-Python: >=3.6
Requires-Dist: odoo14-addon-base-edi
Requires-Dist: odoo14-addon-component-event
Requires-Dist: odoo14-addon-queue-job
Requires-Dist: odoo<14.1dev,>=14.0a
Requires-Dist: pyyaml
